chess_guru/__init__.py
chess_guru/api.py
chess_guru/py.typed
chess_guru/utils.py
chess_guru-0.1.1.dist-info/WHEEL
chess_guru-0.1.1.dist-info/METADATA
chess_guru-0.1.1.dist-info/RECORD
