Metadata-Version: 2.3
Name: chess-guru
Version: 0.1.1
Summary: Async Chess.com public API client
Keywords: chess,chess.com,api,pgn,async,aiohttp
Author: Richard Ramsell
Author-email: Richard Ramsell <richramsell@proton.me>
License: MIT License
Classifier: License :: Other/Proprietary License
Classifier: Development Status :: 3 - Alpha
Classifier: Intended Audience :: Developers
Classifier: Typing :: Typed
Classifier: Programming Language :: Python :: 3
Classifier: Programming Language :: Python :: 3 :: Only
Classifier: Programming Language :: Python :: 3.9
Classifier: Programming Language :: Python :: 3.10
Classifier: Programming Language :: Python :: 3.11
Classifier: Programming Language :: Python :: 3.12
Classifier: Programming Language :: Python :: 3.13
Classifier: Topic :: Games/Entertainment :: Board Games
Classifier: Topic :: Software Development :: Libraries
Requires-Dist: aiohttp>=3.9.0
Requires-Dist: backoff>=2.2.1
Requires-Python: >=3.9
Project-URL: Homepage, https://github.com/rramsell/chess-guru
Project-URL: Repository, https://github.com/rramsell/chess-guru
Project-URL: Issues, https://github.com/rramsell/chess-guru/issues
